mojec_core/__init__.py
mojec_core/api_response.py
mojec_core/firebase.json
mojec_core/middlewares.py
mojec_core/settings.example.py
mojec_core/settings.py
mojec_core/utils.py
mojec_core/app/__init__.py
mojec_core/app/admin.py
mojec_core/app/apps.py
mojec_core/app/signals.py
mojec_core/app/tests.py
mojec_core/app/views.py
mojec_core/app/managers/__init__.py
mojec_core/app/managers/base_redis_manager.py
mojec_core/app/managers/config_manager.py
mojec_core/app/managers/firebase_manager.py
mojec_core/app/managers/push_notification_manager.py
mojec_core/app/managers/user_manager.py
mojec_core/app/migrations/0001_initial.py
mojec_core/app/migrations/0002_auto_20220614_0456.py
mojec_core/app/migrations/0003_auto_20220614_0550.py
mojec_core/app/migrations/0004_auto_20220614_0619.py
mojec_core/app/migrations/0005_auto_20220614_1601.py
mojec_core/app/migrations/0006_auto_20220615_0814.py
mojec_core/app/migrations/0007_auto_20220617_2252.py
mojec_core/app/migrations/0008_auto_20220623_0423.py
mojec_core/app/migrations/0009_auto_20220624_2026.py
mojec_core/app/migrations/0010_alter_config_service.py
mojec_core/app/migrations/0011_auto_20220626_1643.py
mojec_core/app/migrations/0012_auto_20220626_1653.py
mojec_core/app/migrations/0013_auto_20220628_1815.py
mojec_core/app/migrations/0014_meterrequest_orderid.py
mojec_core/app/migrations/0015_meterrequest_status.py
mojec_core/app/migrations/0016_powervend.py
mojec_core/app/migrations/0017_auto_20220714_0637.py
mojec_core/app/migrations/0018_auto_20220717_2210.py
mojec_core/app/migrations/0019_workorder_fee.py
mojec_core/app/migrations/0020_auto_20220804_2126.py
mojec_core/app/migrations/0021_bedroom_workorderbedroom.py
mojec_core/app/migrations/0022_workorderservice_bedrooms.py
mojec_core/app/migrations/0023_auto_20220922_0825.py
mojec_core/app/migrations/__init__.py
mojec_core/app/models/__init__.py
mojec_core/app/models/base.py
mojec_core/app/models/bedroom.py
mojec_core/app/models/card.py
mojec_core/app/models/cart.py
mojec_core-0.2.6.dist-info/LICENSE
mojec_core-0.2.6.dist-info/METADATA
mojec_core-0.2.6.dist-info/WHEEL
mojec_core-0.2.6.dist-info/top_level.txt
mojec_core-0.2.6.dist-info/RECORD
