Metadata-Version: 2.1
Name: mojec-core
Version: 0.2.6
Summary: Mojec core package
Author: Folayemi Bello
Author-email: <bello.folayemi.az@gmail.com>
Keywords: python,mojec
Classifier: Programming Language :: Python :: 3
Classifier: License :: OSI Approved :: MIT License
Classifier: Operating System :: OS Independent
License-File: LICENSE
Requires-Dist: django
Requires-Dist: djangorestframework
Requires-Dist: djangorestframework-simplejwt
Requires-Dist: drf-yasg
Requires-Dist: python-dotenv
Requires-Dist: django-safedelete
Requires-Dist: firebase-admin
Requires-Dist: django-cors-headers
Requires-Dist: redis
Requires-Dist: onesignal-sdk
